gridsearcher/__init__.py
gridsearcher/configs.py
gridsearcher/file_locker.py
gridsearcher/gridsearcher.py
gridsearcher/sbatch.py
gridsearcher/tools.py
gridsearcher-1.1.4.dist-info/licenses/LICENSE
gridsearcher-1.1.4.dist-info/METADATA
gridsearcher-1.1.4.dist-info/WHEEL
gridsearcher-1.1.4.dist-info/top_level.txt
gridsearcher-1.1.4.dist-info/RECORD
