Metadata-Version: 2.4
Name: gridsearcher
Version: 1.1.4
Summary: GridSearcher simplifies running grid searches for machine learning projects in Python, emphasizing parallel execution and GPU scheduling without dependencies on SLURM or other workload managers.
Author-email: Ionut-Vlad Modoranu <ionut-vlad.modoranu@ist.ac.at>
Maintainer-email: Ionut-Vlad Modoranu <ionut-vlad.modoranu@ist.ac.at>
License:                                  Apache License
Project-URL: Repository, https://github.com/IST-DASLab/GridSearcher
Keywords: grid search,automatization,utilitary software,process management,process schedulers
Classifier: License :: OSI Approved :: Apache Software License
License-File: LICENSE
Dynamic: license-file
